mytrigger/my_custom_sensor.py
mytriggernew/my_custom_sensor.py
mytriggernew-0.1.0.dist-info/METADATA
mytriggernew-0.1.0.dist-info/WHEEL
mytriggernew-0.1.0.dist-info/top_level.txt
mytriggernew-0.1.0.dist-info/RECORD
